{
  "data": {
    "article": {},
    "attachments": {},
    "author_id": "2063169843671793664",
    "conversation_id": "2064603001512509847",
    "created_at": "2026-06-10T07:34:56.000Z",
    "edit_controls": {
      "editable_until": "2026-06-10T08:34:56.000Z",
      "edits_remaining": 5,
      "is_edit_eligible": false
    },
    "edit_history_tweet_ids": [
      "2064612262154002651"
    ],
    "entities": {
      "mentions": [
        {
          "end": 6,
          "id": "1456872541952229379",
          "start": 0,
          "username": "txqv3"
        }
      ]
    },
    "geo": {},
    "id": "2064612262154002651",
    "in_reply_to_user_id": "1456872541952229379",
    "lang": "zh",
    "note_tweet": {
      "entities": {}
    },
    "possibly_sensitive": false,
    "public_metrics": {
      "bookmark_count": 0,
      "impression_count": 0,
      "like_count": 0,
      "quote_count": 0,
      "reply_count": 0,
      "retweet_count": 0
    },
    "referenced_tweets": [
      {
        "id": "2064611914660114511",
        "type": "replied_to"
      }
    ],
    "reply_settings": "everyone",
    "text": "@txqv3 我把桡动脉直接挑断了也没死掉😔"
  },
  "includes": {
    "tweets": [
      {
        "article": {},
        "attachments": {},
        "author_id": "2063169843671793664",
        "conversation_id": "2064603001512509847",
        "created_at": "2026-06-10T07:34:56.000Z",
        "edit_controls": {
          "editable_until": "2026-06-10T08:34:56.000Z",
          "edits_remaining": 5,
          "is_edit_eligible": false
        },
        "edit_history_tweet_ids": [
          "2064612262154002651"
        ],
        "entities": {
          "mentions": [
            {
              "end": 6,
              "id": "1456872541952229379",
              "start": 0,
              "username": "txqv3"
            }
          ]
        },
        "geo": {},
        "id": "2064612262154002651",
        "in_reply_to_user_id": "1456872541952229379",
        "lang": "zh",
        "note_tweet": {
          "entities": {}
        },
        "possibly_sensitive": false,
        "public_metrics": {
          "bookmark_count": 0,
          "impression_count": 0,
          "like_count": 0,
          "quote_count": 0,
          "reply_count": 0,
          "retweet_count": 0
        },
        "referenced_tweets": [
          {
            "id": "2064611914660114511",
            "type": "replied_to"
          }
        ],
        "reply_settings": "everyone",
        "text": "@txqv3 我把桡动脉直接挑断了也没死掉😔"
      },
      {
        "article": {},
        "attachments": {},
        "author_id": "1456872541952229379",
        "conversation_id": "2064603001512509847",
        "created_at": "2026-06-10T07:33:33.000Z",
        "edit_controls": {
          "editable_until": "2026-06-10T08:33:33.000Z",
          "edits_remaining": 5,
          "is_edit_eligible": false
        },
        "edit_history_tweet_ids": [
          "2064611914660114511"
        ],
        "entities": {
          "mentions": [
            {
              "end": 9,
              "id": "2063169843671793664",
              "start": 0,
              "username": "Mercyvxv"
            }
          ]
        },
        "geo": {},
        "id": "2064611914660114511",
        "in_reply_to_user_id": "2063169843671793664",
        "lang": "zh",
        "note_tweet": {
          "entities": {}
        },
        "possibly_sensitive": false,
        "public_metrics": {
          "bookmark_count": 0,
          "impression_count": 1,
          "like_count": 1,
          "quote_count": 0,
          "reply_count": 1,
          "retweet_count": 0
        },
        "referenced_tweets": [
          {
            "id": "2064603001512509847",
            "type": "replied_to"
          }
        ],
        "reply_settings": "everyone",
        "text": "@Mercyvxv 要保证不凝血的。。。不推荐尝试"
      }
    ],
    "users": [
      {
        "created_at": "2026-06-06T08:06:56.000Z",
        "description": "我复活了。互fo私信 出普瑞dpt",
        "id": "2063169843671793664",
        "name": "Mercy",
        "profile_image_url": "https://pbs.twimg.com/profile_images/2063171578217766912/yFJpjZ2G_normal.jpg",
        "protected": false,
        "public_metrics": {
          "followers_count": 206,
          "following_count": 192,
          "like_count": 360,
          "listed_count": 1,
          "media_count": 2,
          "tweet_count": 93
        },
        "username": "Mercyvxv",
        "verified": false
      },
      {
        "created_at": "2021-11-06T06:34:26.000Z",
        "description": "底层农村人，并非做题家，基本每天长时间推特在线，爱好分享一些自己的魔改手办收藏，有兴趣可以私我进q群玩，对各种卡牌也很有兴趣，有所收藏，做梦高手，逃避人生高手，另外我被全身烧伤过，身体残疾，状态很差，有没有给我施舍点的……",
        "id": "1456872541952229379",
        "location": "未知",
        "name": "躲在被子里的梦梦",
        "pinned_tweet_id": "2058423290138329200",
        "profile_image_url": "https://pbs.twimg.com/profile_images/1975479370476363779/b9hRy7Qe_normal.jpg",
        "protected": false,
        "public_metrics": {
          "followers_count": 2179,
          "following_count": 1302,
          "like_count": 71280,
          "listed_count": 6,
          "media_count": 1540,
          "tweet_count": 19789
        },
        "username": "txqv3",
        "verified": true
      }
    ]
  }
}