{
  "data": {
    "article": {},
    "attachments": {},
    "author_id": "2063169843671793664",
    "conversation_id": "2073061350050583041",
    "created_at": "2026-07-03T15:08:36.000Z",
    "edit_controls": {
      "editable_until": "2026-07-03T16:08:36.000Z",
      "edits_remaining": 5,
      "is_edit_eligible": true
    },
    "edit_history_tweet_ids": [
      "2073061350050583041"
    ],
    "entities": {},
    "geo": {},
    "id": "2073061350050583041",
    "lang": "zh",
    "note_tweet": {
      "entities": {}
    },
    "possibly_sensitive": false,
    "public_metrics": {
      "bookmark_count": 0,
      "impression_count": 0,
      "like_count": 1,
      "quote_count": 0,
      "reply_count": 0,
      "retweet_count": 0
    },
    "reply_settings": "everyone",
    "text": "一天一针安定，躯体化远离我。"
  },
  "includes": {
    "tweets": [
      {
        "article": {},
        "attachments": {},
        "author_id": "2063169843671793664",
        "conversation_id": "2073061350050583041",
        "created_at": "2026-07-03T15:08:36.000Z",
        "edit_controls": {
          "editable_until": "2026-07-03T16:08:36.000Z",
          "edits_remaining": 5,
          "is_edit_eligible": true
        },
        "edit_history_tweet_ids": [
          "2073061350050583041"
        ],
        "entities": {},
        "geo": {},
        "id": "2073061350050583041",
        "lang": "zh",
        "note_tweet": {
          "entities": {}
        },
        "possibly_sensitive": false,
        "public_metrics": {
          "bookmark_count": 0,
          "impression_count": 0,
          "like_count": 1,
          "quote_count": 0,
          "reply_count": 0,
          "retweet_count": 0
        },
        "reply_settings": "everyone",
        "text": "一天一针安定，躯体化远离我。"
      }
    ],
    "users": [
      {
        "created_at": "2026-06-06T08:06:56.000Z",
        "description": "我复活了。发病日记。\n\nBD/BPD/DPDR，💊🔪🩸。",
        "id": "2063169843671793664",
        "name": "Mercy",
        "pinned_tweet_id": "2072980468744765809",
        "profile_image_url": "https://pbs.twimg.com/profile_images/2063171578217766912/yFJpjZ2G_normal.jpg",
        "protected": false,
        "public_metrics": {
          "followers_count": 242,
          "following_count": 213,
          "like_count": 413,
          "listed_count": 1,
          "media_count": 5,
          "tweet_count": 130
        },
        "url": "",
        "username": "Mercyvxv",
        "verified": false
      }
    ]
  }
}